<?xml version="1.0" encoding="utf-8"?>
<Deployment xmlns="http://schemas.microsoft.com/windowsphone/2012/deployment" AppPlatformVersion="8.0">
  <DefaultLanguage xmlns="" code="en" />
  <Languages xmlns="">
    <Language code="nl" />
  </Languages>
  <App xmlns="" ProductID="{6be2b516-0619-40c5-ac93-da0d4de48f5c}" Title="Rijksmuseum Lockscreen" RuntimeType="Silverlight" Version="1.0.0.0" Genre="apps.normal" Author="M.R. Post" Description="Display the Rijksmuseum paintings on your lockscreen" Publisher="RijksLockScreen.WP" PublisherID="{6d328683-8ac1-4118-979a-f42cf7cd930f}">
    <IconPath IsRelative="true" IsResource="false">Assets\ApplicationIcon.png</IconPath>
    <Capabilities>
      <Capability Name="ID_CAP_NETWORKING" />
    </Capabilities>
    <Tasks>
      <DefaultTask Name="_default" NavigationPage="MainPage.xaml" />
    </Tasks>
    <Tokens>
      <PrimaryToken TokenID="RijksLockScreen.WPToken" TaskName="_default">
        <TemplateFlip>
          <SmallImageURI IsRelative="true" IsResource="false">
          </SmallImageURI>
          <Count>0</Count>
          <BackgroundImageURI IsRelative="true" IsResource="false">
          </BackgroundImageURI>
          <Title>
          </Title>
          <BackContent>
          </BackContent>
          <BackBackgroundImageURI IsRelative="true" IsResource="false">
          </BackBackgroundImageURI>
          <BackTitle>
          </BackTitle>
          <LargeBackgroundImageURI IsRelative="true" IsResource="false">
          </LargeBackgroundImageURI>
          <LargeBackContent />
          <LargeBackBackgroundImageURI IsRelative="true" IsResource="false">
          </LargeBackBackgroundImageURI>
          <DeviceLockImageURI IsRelative="true" IsResource="false">
          </DeviceLockImageURI>
          <HasLarge>True</HasLarge>
        </TemplateFlip>
      </PrimaryToken>
    </Tokens>
    <Extensions>
      <Extension ExtensionName="LockScreen_Background" ConsumerID="{111DFF24-AA15-4A96-8006-2BFF8122084F}" TaskID="_default" />
    </Extensions>
    <ScreenResolutions>
      <ScreenResolution Name="ID_RESOLUTION_WVGA" />
      <ScreenResolution Name="ID_RESOLUTION_WXGA" />
      <ScreenResolution Name="ID_RESOLUTION_HD720P" />
    </ScreenResolutions>
  </App>
</Deployment>